lighthouse_scoring_calculator_v10/__init__.py
lighthouse_scoring_calculator_v10/__main__.py
lighthouse_scoring_calculator_v10/calculator.py
lighthouse_scoring_calculator_v10/example.py
lighthouse_scoring_calculator_v10/metrics.py
lighthouse_scoring_calculator_v10/util.py
lighthouse_scoring_calculator_v10-1.0.13.dist-info/LICENSE
lighthouse_scoring_calculator_v10-1.0.13.dist-info/METADATA
lighthouse_scoring_calculator_v10-1.0.13.dist-info/WHEEL
lighthouse_scoring_calculator_v10-1.0.13.dist-info/top_level.txt
lighthouse_scoring_calculator_v10-1.0.13.dist-info/RECORD
